structured_data_generator/__init__.py
structured_data_generator/config/__init__.py
structured_data_generator/config/default_config.py
structured_data_generator/core/__init__.py
structured_data_generator/core/constraints.py
structured_data_generator/core/generators.py
structured_data_generator/core/utils.py
structured_data_generator/io/__init__.py
structured_data_generator/io/csv_handler.py
structured_data_generator/io/json_handler.py
structured_data_generator/profiling/__init__.py
structured_data_generator/profiling/profiler.py
structured_data_generator/scripts/__init__.py
structured_data_generator/scripts/generate_dataset.py
structured_data_generator/scripts/profile_dataset.py
synthetic_data_maker-0.4.0.dist-info/licenses/LICENSE
synthetic_data_maker-0.4.0.dist-info/METADATA
synthetic_data_maker-0.4.0.dist-info/WHEEL
synthetic_data_maker-0.4.0.dist-info/entry_points.txt
synthetic_data_maker-0.4.0.dist-info/top_level.txt
synthetic_data_maker-0.4.0.dist-info/RECORD
